{
  "base_email": {
    "en": {
      "footer_note": "You received this email because it relates to your CAP account or activity.",
      "unsubscribe": "Unsubscribe"
    },
    "pt": {
      "footer_note": "Você recebeu este e-mail porque ele se relaciona à sua conta ou atividade na CAP.",
      "unsubscribe": "Cancelar inscrição"
    }
  },
  "waiting_list_confirmation": {
    "en": {
      "title": "You're on the List",
      "message": "<h2>Welcome to CAP</h2><p>Thanks for joining the CAP waitlist. You’re now in line to get early access to the Cardano Analytics Platform.</p><h3>What’s next?</h3><ul style=\"margin: 12px 0 0 0; padding-left: 18px;\"><li style=\"margin: 0 0 8px 0;\">We’ll email you updates about the launch and upcoming features.</li><li style=\"margin: 0 0 8px 0;\">Join our Telegram channel: <a href=\"https://t.me/cardanoanalytics\" style=\"color:#2563eb; text-decoration:none;\">t.me/cardanoanalytics</a></li><li style=\"margin: 0;\">Feel free to share your referral link with friends who may be interested: <a href=\"{referral_link}\" style=\"color:#2563eb; text-decoration:none;\">Invite friends</a>.</li></ul><p style=\"margin: 16px 0 0 0;\">We’re excited to have you with us.</p>"
    },
    "pt": {
      "title": "Você está na lista",
      "message": "<h2>Bem-vindo à CAP</h2><p>Obrigado por entrar na lista de espera da CAP. Você está na fila para ter acesso antecipado à Cardano Analytics Platform.</p><h3>O que vem a seguir?</h3><ul style=\"margin: 12px 0 0 0; padding-left: 18px;\"><li style=\"margin: 0 0 8px 0;\">Enviaremos atualizações sobre o lançamento e novos recursos.</li><li style=\"margin: 0 0 8px 0;\">Entre no nosso canal no Telegram: <a href=\"https://t.me/cardanoanalytics\" style=\"color:#2563eb; text-decoration:none;\">t.me/cardanoanalytics</a></li><li style=\"margin: 0;\">Se quiser, compartilhe seu link de convite com amigos que possam se interessar: <a href=\"{referral_link}\" style=\"color:#2563eb; text-decoration:none;\">Convidar amigos</a>.</li></ul><p style=\"margin: 16px 0 0 0;\">Ficamos felizes em ter você com a gente.</p>"
    }
  },
  "user_registration": {
    "en": {
      "title": "Confirm your email for CAP",
      "hello": "Hi",
      "instructions": "Click the button below to confirm your email and finish your signup.",
      "confirm": "Confirm email",
      "footer": "If you didn’t request this, you can ignore this email."
    },
    "pt": {
      "title": "Confirme seu e-mail para a CAP",
      "hello": "Olá",
      "instructions": "Clique no botão abaixo para confirmar seu e-mail e concluir seu cadastro.",
      "confirm": "Confirmar e-mail",
      "footer": "Se você não solicitou isto, basta ignorar este e-mail."
    }
  },
  "user_confirmation_resent": {
    "en": {
      "title": "We resent your confirmation email",
      "lead": "We sent you a new confirmation email. Please check your inbox (and spam folder).",
      "help": "If you don’t see it, try again in a few minutes or contact support.",
      "footer": "This is an automated message from the Cardano Analytics Platform (CAP)."
    },
    "pt": {
      "title": "Reenviamos seu e-mail de confirmação",
      "lead": "Enviamos um novo e-mail de confirmação. Verifique sua caixa de entrada (e o spam).",
      "help": "Se ainda não aparecer, tente novamente em alguns minutos ou contate o suporte.",
      "footer": "Mensagem automática da Cardano Analytics Platform (CAP)."
    }
  },
  "user_confirmed": {
    "en": {
      "title": "Welcome to CAP!",
      "lead": "Your email has been successfully confirmed.",
      "next": "You can now sign in and start exploring analytics, queries, and dashboards.",
      "footer": "Thanks for joining the Cardano Analytics Platform (CAP)."
    },
    "pt": {
      "title": "Bem-vindo(a) à CAP!",
      "lead": "Seu e-mail foi confirmado com sucesso.",
      "next": "Agora você pode entrar e começar a explorar análises, consultas e dashboards.",
      "footer": "Obrigado por se juntar à Cardano Analytics Platform (CAP)."
    }
  },
  "oauth_login": {
    "en": {
      "title": "New sign-in notification",
      "lead": "A new sign-in just occurred via",
      "tip": "If this wasn’t you, please reset your password and check your account activity.",
      "footer": "Security notice from the Cardano Analytics Platform (CAP)."
    },
    "pt": {
      "title": "Novo login detectado",
      "lead": "Um novo login ocorreu via",
      "tip": "Se não foi você, redefina sua senha e verifique a atividade da conta.",
      "footer": "Aviso de segurança da Cardano Analytics Platform (CAP)."
    }
  },
  "wallet_login": {
    "en": {
      "title": "New wallet sign-in",
      "lead": "A sign-in was made using your Cardano wallet:",
      "tip": "If you don’t recognize this, review your sessions and secure your account.",
      "footer": "Security notice from the Cardano Analytics Platform (CAP)."
    },
    "pt": {
      "title": "Novo login por carteira",
      "lead": "Um login foi feito usando sua carteira Cardano:",
      "tip": "Se você não reconhece, revise suas sessões e proteja sua conta.",
      "footer": "Aviso de segurança da Cardano Analytics Platform (CAP)."
    }
  },
  "user_email_verified": {
    "en": {
      "preheader": "Your email address has been successfully verified.",
      "title": "Email verified",
      "lead": "Thanks! Your email address has been successfully verified.",
      "next": "If you have access enabled, you can now sign in and start using CAP.",
      "cta_label": "Open CAP",
      "footer": "This is an automated message from the Cardano Analytics Platform (CAP)."
    },
    "pt": {
      "preheader": "Seu endereço de e-mail foi verificado com sucesso.",
      "title": "E-mail verificado",
      "lead": "Obrigado! Seu endereço de e-mail foi verificado com sucesso.",
      "next": "Se o seu acesso estiver habilitado, você já pode entrar e começar a usar a CAP.",
      "cta_label": "Abrir CAP",
      "footer": "Mensagem automática da Cardano Analytics Platform (CAP)."
    }
  },
  "user_access_granted": {
    "en": {
      "preheader": "Your CAP account is now active.",
      "title": "Access granted",
      "lead": "Your account has been approved and is now active.",
      "next": "You can sign in and start exploring analytics, queries, and dashboards.",
      "cta_label": "Open CAP",
      "footer": "Welcome aboard — this message was sent by the Cardano Analytics Platform (CAP)."
    },
    "pt": {
      "preheader": "Sua conta CAP agora está ativa.",
      "title": "Acesso liberado",
      "lead": "Sua conta foi aprovada e agora está ativa.",
      "next": "Você já pode entrar e começar a explorar análises, consultas e dashboards.",
      "cta_label": "Abrir CAP",
      "footer": "Bem-vindo(a) — mensagem enviada pela Cardano Analytics Platform (CAP)."
    }
  },
  "waitlist_promoted": {
    "en": {
      "preheader": "Good news: your CAP access is now available.",
      "title": "You’re in",
      "lead": "Good news, your waitlist request has been approved.",
      "next": "You can now sign in and start using CAP.",
      "cta_label": "Open CAP",
      "footer": "This is an automated message from the Cardano Analytics Platform (CAP)."
    },
    "pt": {
      "preheader": "Boas notícias: seu acesso à CAP já está disponível.",
      "title": "Acesso liberado",
      "lead": "Boas notícias, seu pedido na lista de espera foi aprovado.",
      "next": "Agora você já pode entrar e começar a usar a CAP.",
      "cta_label": "Abrir CAP",
      "footer": "Mensagem automática da Cardano Analytics Platform (CAP)."
    }
  },
  "admin_user_confirmed": {
    "en": {
      "preheader": "A user has just been confirmed/approved in your CAP instance.",
      "title": "User confirmed",
      "lead": "A user account has just been confirmed/approved on {app_name}.",
      "username_label": "Username",
      "email_label": "Email",
      "source_label": "Source",
      "source_password": "Email & password",
      "source_google": "Google OAuth",
      "source_cardano": "Cardano wallet",
      "source_waitlist": "Waitlist",
      "manage_hint": "You can review the user’s details and permissions in the admin panel.",
      "manage_link_label": "Open CAP",
      "footer": "You’re receiving this message because admin notifications are enabled."
    },
    "pt": {
      "preheader": "Um usuário acabou de ser confirmado/aprovado na sua instância da CAP.",
      "title": "Usuário confirmado",
      "lead": "Uma conta de usuário acabou de ser confirmada/aprovada no {app_name}.",
      "username_label": "Usuário",
      "email_label": "E-mail",
      "source_label": "Origem",
      "source_password": "E-mail e senha",
      "source_google": "Google OAuth",
      "source_cardano": "Carteira Cardano",
      "source_waitlist": "Lista de espera",
      "manage_hint": "Você pode revisar os detalhes e permissões do usuário no painel de admin.",
      "manage_link_label": "Abrir CAP",
      "footer": "Você está recebendo esta mensagem porque as notificações de admin estão habilitadas."
    }
  },
  "user_access_revoked": {
    "en": {
      "preheader": "Your CAP account access has been updated.",
      "title": "Access updated",
      "lead": "Your account access has been revoked or disabled at this time.",
      "help": "If you believe this is a mistake, please contact support.",
      "cta_label": "Open CAP",
      "footer": "This is an automated message from the Cardano Analytics Platform (CAP)."
    },
    "pt": {
      "preheader": "O acesso da sua conta CAP foi atualizado.",
      "title": "Acesso atualizado",
      "lead": "O acesso da sua conta foi revogado ou desabilitado no momento.",
      "help": "Se você acredita que isso é um engano, por favor contate o suporte.",
      "cta_label": "Abrir CAP",
      "footer": "Mensagem automática da Cardano Analytics Platform (CAP)."
    }
  }
}
